7th-resnest-resnext-densenet-0-98840.py
__init__.py
pytorch_model.py
leicv-0.0.1.dist-info/METADATA
leicv-0.0.1.dist-info/WHEEL
leicv-0.0.1.dist-info/licenses/LICENSE
leicv-0.0.1.dist-info/RECORD
