Metadata-Version: 2.1
Name: LeiCV
Version: 0.0.1
Summary: LeiCV for Image Classification.
Project-URL: Homepage, https://github.com/Letty51/Letty51.github.io
Author-email: L <123641640@qq.com>
License: MIT License
License-File: LICENSE
Classifier: License :: OSI Approved :: MIT License
Classifier: Operating System :: OS Independent
Classifier: Programming Language :: Python :: 3
Requires-Python: >=3.7
